{"nodes": [{"id": "s_mls_v2_frontend_components_similarproperties_tsx", "label": "SimilarProperties.tsx", "file_type": "code", "source_file": "S:\\mls-v2\\frontend\\components\\SimilarProperties.tsx", "source_location": "L1"}, {"id": "similarproperties_fetchsimilarproperties", "label": "fetchSimilarProperties()", "file_type": "code", "source_file": "S:\\mls-v2\\frontend\\components\\SimilarProperties.tsx", "source_location": "L51"}, {"id": "similarproperties_formatsimilarpropertyprice", "label": "formatSimilarPropertyPrice()", "file_type": "code", "source_file": "S:\\mls-v2\\frontend\\components\\SimilarProperties.tsx", "source_location": "L130"}, {"id": "similarproperties_getsimilarpropertyimage", "label": "getSimilarPropertyImage()", "file_type": "code", "source_file": "S:\\mls-v2\\frontend\\components\\SimilarProperties.tsx", "source_location": "L141"}, {"id": "similarproperties_handlepropertyclick", "label": "handlePropertyClick()", "file_type": "code", "source_file": "S:\\mls-v2\\frontend\\components\\SimilarProperties.tsx", "source_location": "L155"}], "edges": [{"source": "s_mls_v2_frontend_components_similarproperties_tsx", "target": "react", "relation": "imports_from", "confidence": "EXTRACTED", "source_file": "S:\\mls-v2\\frontend\\components\\SimilarProperties.tsx", "source_location": "L3", "weight": 1.0}, {"source": "s_mls_v2_frontend_components_similarproperties_tsx", "target": "image", "relation": "imports_from", "confidence": "EXTRACTED", "source_file": "S:\\mls-v2\\frontend\\components\\SimilarProperties.tsx", "source_location": "L4", "weight": 1.0}, {"source": "s_mls_v2_frontend_components_similarproperties_tsx", "target": "lucide_react", "relation": "imports_from", "confidence": "EXTRACTED", "source_file": "S:\\mls-v2\\frontend\\components\\SimilarProperties.tsx", "source_location": "L5", "weight": 1.0}, {"source": "s_mls_v2_frontend_components_similarproperties_tsx", "target": "design_system_utils", "relation": "imports_from", "confidence": "EXTRACTED", "source_file": "S:\\mls-v2\\frontend\\components\\SimilarProperties.tsx", "source_location": "L6", "weight": 1.0}, {"source": "s_mls_v2_frontend_components_similarproperties_tsx", "target": "link", "relation": "imports_from", "confidence": "EXTRACTED", "source_file": "S:\\mls-v2\\frontend\\components\\SimilarProperties.tsx", "source_location": "L7", "weight": 1.0}, {"source": "s_mls_v2_frontend_components_similarproperties_tsx", "target": "propertyutils", "relation": "imports_from", "confidence": "EXTRACTED", "source_file": "S:\\mls-v2\\frontend\\components\\SimilarProperties.tsx", "source_location": "L8", "weight": 1.0}, {"source": "s_mls_v2_frontend_components_similarproperties_tsx", "target": "openinnewtab", "relation": "imports_from", "confidence": "EXTRACTED", "source_file": "S:\\mls-v2\\frontend\\components\\SimilarProperties.tsx", "source_location": "L9", "weight": 1.0}, {"source": "s_mls_v2_frontend_components_similarproperties_tsx", "target": "similarproperties_fetchsimilarproperties", "relation": "contains", "confidence": "EXTRACTED", "source_file": "S:\\mls-v2\\frontend\\components\\SimilarProperties.tsx", "source_location": "L51", "weight": 1.0}, {"source": "s_mls_v2_frontend_components_similarproperties_tsx", "target": "similarproperties_formatsimilarpropertyprice", "relation": "contains", "confidence": "EXTRACTED", "source_file": "S:\\mls-v2\\frontend\\components\\SimilarProperties.tsx", "source_location": "L130", "weight": 1.0}, {"source": "s_mls_v2_frontend_components_similarproperties_tsx", "target": "similarproperties_getsimilarpropertyimage", "relation": "contains", "confidence": "EXTRACTED", "source_file": "S:\\mls-v2\\frontend\\components\\SimilarProperties.tsx", "source_location": "L141", "weight": 1.0}, {"source": "s_mls_v2_frontend_components_similarproperties_tsx", "target": "similarproperties_handlepropertyclick", "relation": "contains", "confidence": "EXTRACTED", "source_file": "S:\\mls-v2\\frontend\\components\\SimilarProperties.tsx", "source_location": "L155", "weight": 1.0}], "raw_calls": [{"caller_nid": "similarproperties_fetchsimilarproperties", "callee": "setIsLoading", "source_file": "S:\\mls-v2\\frontend\\components\\SimilarProperties.tsx", "source_location": "L53"}, {"caller_nid": "similarproperties_fetchsimilarproperties", "callee": "setError", "source_file": "S:\\mls-v2\\frontend\\components\\SimilarProperties.tsx", "source_location": "L54"}, {"caller_nid": "similarproperties_fetchsimilarproperties", "callee": "set", "source_file": "S:\\mls-v2\\frontend\\components\\SimilarProperties.tsx", "source_location": "L64"}, {"caller_nid": "similarproperties_fetchsimilarproperties", "callee": "parseFloat", "source_file": "S:\\mls-v2\\frontend\\components\\SimilarProperties.tsx", "source_location": "L69"}, {"caller_nid": "similarproperties_fetchsimilarproperties", "callee": "isNaN", "source_file": "S:\\mls-v2\\frontend\\components\\SimilarProperties.tsx", "source_location": "L70"}, {"caller_nid": "similarproperties_fetchsimilarproperties", "callee": "set", "source_file": "S:\\mls-v2\\frontend\\components\\SimilarProperties.tsx", "source_location": "L71"}, {"caller_nid": "similarproperties_fetchsimilarproperties", "callee": "toString", "source_file": "S:\\mls-v2\\frontend\\components\\SimilarProperties.tsx", "source_location": "L71"}, {"caller_nid": "similarproperties_fetchsimilarproperties", "callee": "floor", "source_file": "S:\\mls-v2\\frontend\\components\\SimilarProperties.tsx", "source_location": "L71"}, {"caller_nid": "similarproperties_fetchsimilarproperties", "callee": "set", "source_file": "S:\\mls-v2\\frontend\\components\\SimilarProperties.tsx", "source_location": "L72"}, {"caller_nid": "similarproperties_fetchsimilarproperties", "callee": "toString", "source_file": "S:\\mls-v2\\frontend\\components\\SimilarProperties.tsx", "source_location": "L72"}, {"caller_nid": "similarproperties_fetchsimilarproperties", "callee": "ceil", "source_file": "S:\\mls-v2\\frontend\\components\\SimilarProperties.tsx", "source_location": "L72"}, {"caller_nid": "similarproperties_fetchsimilarproperties", "callee": "set", "source_file": "S:\\mls-v2\\frontend\\components\\SimilarProperties.tsx", "source_location": "L78"}, {"caller_nid": "similarproperties_fetchsimilarproperties", "callee": "toString", "source_file": "S:\\mls-v2\\frontend\\components\\SimilarProperties.tsx", "source_location": "L78"}, {"caller_nid": "similarproperties_fetchsimilarproperties", "callee": "max", "source_file": "S:\\mls-v2\\frontend\\components\\SimilarProperties.tsx", "source_location": "L78"}, {"caller_nid": "similarproperties_fetchsimilarproperties", "callee": "set", "source_file": "S:\\mls-v2\\frontend\\components\\SimilarProperties.tsx", "source_location": "L79"}, {"caller_nid": "similarproperties_fetchsimilarproperties", "callee": "toString", "source_file": "S:\\mls-v2\\frontend\\components\\SimilarProperties.tsx", "source_location": "L79"}, {"caller_nid": "similarproperties_fetchsimilarproperties", "callee": "log", "source_file": "S:\\mls-v2\\frontend\\components\\SimilarProperties.tsx", "source_location": "L84"}, {"caller_nid": "similarproperties_fetchsimilarproperties", "callee": "fetch", "source_file": "S:\\mls-v2\\frontend\\components\\SimilarProperties.tsx", "source_location": "L86"}, {"caller_nid": "similarproperties_fetchsimilarproperties", "callee": "json", "source_file": "S:\\mls-v2\\frontend\\components\\SimilarProperties.tsx", "source_location": "L92"}, {"caller_nid": "similarproperties_fetchsimilarproperties", "callee": "map", "source_file": "S:\\mls-v2\\frontend\\components\\SimilarProperties.tsx", "source_location": "L95"}, {"caller_nid": "similarproperties_fetchsimilarproperties", "callee": "slice", "source_file": "S:\\mls-v2\\frontend\\components\\SimilarProperties.tsx", "source_location": "L95"}, {"caller_nid": "similarproperties_fetchsimilarproperties", "callee": "filter", "source_file": "S:\\mls-v2\\frontend\\components\\SimilarProperties.tsx", "source_location": "L95"}, {"caller_nid": "similarproperties_fetchsimilarproperties", "callee": "log", "source_file": "S:\\mls-v2\\frontend\\components\\SimilarProperties.tsx", "source_location": "L116"}, {"caller_nid": "similarproperties_fetchsimilarproperties", "callee": "setSimilarProperties", "source_file": "S:\\mls-v2\\frontend\\components\\SimilarProperties.tsx", "source_location": "L117"}, {"caller_nid": "similarproperties_fetchsimilarproperties", "callee": "error", "source_file": "S:\\mls-v2\\frontend\\components\\SimilarProperties.tsx", "source_location": "L119"}, {"caller_nid": "similarproperties_fetchsimilarproperties", "callee": "setError", "source_file": "S:\\mls-v2\\frontend\\components\\SimilarProperties.tsx", "source_location": "L120"}, {"caller_nid": "similarproperties_fetchsimilarproperties", "callee": "setIsLoading", "source_file": "S:\\mls-v2\\frontend\\components\\SimilarProperties.tsx", "source_location": "L122"}, {"caller_nid": "similarproperties_formatsimilarpropertyprice", "callee": "parseFloat", "source_file": "S:\\mls-v2\\frontend\\components\\SimilarProperties.tsx", "source_location": "L133"}, {"caller_nid": "similarproperties_formatsimilarpropertyprice", "callee": "isNaN", "source_file": "S:\\mls-v2\\frontend\\components\\SimilarProperties.tsx", "source_location": "L134"}, {"caller_nid": "similarproperties_formatsimilarpropertyprice", "callee": "toLocaleString", "source_file": "S:\\mls-v2\\frontend\\components\\SimilarProperties.tsx", "source_location": "L135"}, {"caller_nid": "similarproperties_formatsimilarpropertyprice", "callee": "toLocaleString", "source_file": "S:\\mls-v2\\frontend\\components\\SimilarProperties.tsx", "source_location": "L137"}, {"caller_nid": "similarproperties_handlepropertyclick", "callee": "openInNewTab", "source_file": "S:\\mls-v2\\frontend\\components\\SimilarProperties.tsx", "source_location": "L156"}, {"caller_nid": "similarproperties_handlepropertyclick", "callee": "getDetailUrl", "source_file": "S:\\mls-v2\\frontend\\components\\SimilarProperties.tsx", "source_location": "L156"}]}