{"nodes": [{"id": "s_mls_v2_frontend_components_listing_fullgallerymodal_tsx", "label": "FullGalleryModal.tsx", "file_type": "code", "source_file": "S:\\mls-v2\\frontend\\components\\listing\\FullGalleryModal.tsx", "source_location": "L1"}, {"id": "fullgallerymodal_onkey", "label": "onKey()", "file_type": "code", "source_file": "S:\\mls-v2\\frontend\\components\\listing\\FullGalleryModal.tsx", "source_location": "L39"}], "edges": [{"source": "s_mls_v2_frontend_components_listing_fullgallerymodal_tsx", "target": "react", "relation": "imports_from", "confidence": "EXTRACTED", "source_file": "S:\\mls-v2\\frontend\\components\\listing\\FullGalleryModal.tsx", "source_location": "L4", "weight": 1.0}, {"source": "s_mls_v2_frontend_components_listing_fullgallerymodal_tsx", "target": "react_dom", "relation": "imports_from", "confidence": "EXTRACTED", "source_file": "S:\\mls-v2\\frontend\\components\\listing\\FullGalleryModal.tsx", "source_location": "L5", "weight": 1.0}, {"source": "s_mls_v2_frontend_components_listing_fullgallerymodal_tsx", "target": "lucide_react", "relation": "imports_from", "confidence": "EXTRACTED", "source_file": "S:\\mls-v2\\frontend\\components\\listing\\FullGalleryModal.tsx", "source_location": "L6", "weight": 1.0}, {"source": "s_mls_v2_frontend_components_listing_fullgallerymodal_tsx", "target": "framer_motion", "relation": "imports_from", "confidence": "EXTRACTED", "source_file": "S:\\mls-v2\\frontend\\components\\listing\\FullGalleryModal.tsx", "source_location": "L7", "weight": 1.0}, {"source": "s_mls_v2_frontend_components_listing_fullgallerymodal_tsx", "target": "image", "relation": "imports_from", "confidence": "EXTRACTED", "source_file": "S:\\mls-v2\\frontend\\components\\listing\\FullGalleryModal.tsx", "source_location": "L8", "weight": 1.0}, {"source": "s_mls_v2_frontend_components_listing_fullgallerymodal_tsx", "target": "fullgallerymodal_onkey", "relation": "contains", "confidence": "EXTRACTED", "source_file": "S:\\mls-v2\\frontend\\components\\listing\\FullGalleryModal.tsx", "source_location": "L39", "weight": 1.0}], "raw_calls": [{"caller_nid": "fullgallerymodal_onkey", "callee": "onClose", "source_file": "S:\\mls-v2\\frontend\\components\\listing\\FullGalleryModal.tsx", "source_location": "L40"}, {"caller_nid": "fullgallerymodal_onkey", "callee": "setIndex", "source_file": "S:\\mls-v2\\frontend\\components\\listing\\FullGalleryModal.tsx", "source_location": "L42"}, {"caller_nid": "fullgallerymodal_onkey", "callee": "setIndex", "source_file": "S:\\mls-v2\\frontend\\components\\listing\\FullGalleryModal.tsx", "source_location": "L43"}]}