{"nodes": [{"id": "desktopnav", "label": "DesktopNav.tsx", "file_type": "code", "source_file": "frontend\\components\\header\\DesktopNav.tsx", "source_location": "L1"}, {"id": "desktopnav_desktopnav", "label": "DesktopNav()", "file_type": "code", "source_file": "frontend\\components\\header\\DesktopNav.tsx", "source_location": "L24"}], "edges": [{"source": "desktopnav", "target": "link", "relation": "imports_from", "confidence": "EXTRACTED", "source_file": "frontend\\components\\header\\DesktopNav.tsx", "source_location": "L3", "weight": 1.0}, {"source": "desktopnav", "target": "image", "relation": "imports_from", "confidence": "EXTRACTED", "source_file": "frontend\\components\\header\\DesktopNav.tsx", "source_location": "L4", "weight": 1.0}, {"source": "desktopnav", "target": "navigation", "relation": "imports_from", "confidence": "EXTRACTED", "source_file": "frontend\\components\\header\\DesktopNav.tsx", "source_location": "L6", "weight": 1.0}, {"source": "desktopnav", "target": "framer_motion", "relation": "imports_from", "confidence": "EXTRACTED", "source_file": "frontend\\components\\header\\DesktopNav.tsx", "source_location": "L7", "weight": 1.0}, {"source": "desktopnav", "target": "lucide_react", "relation": "imports_from", "confidence": "EXTRACTED", "source_file": "frontend\\components\\header\\DesktopNav.tsx", "source_location": "L8", "weight": 1.0}, {"source": "desktopnav", "target": "provinceselector", "relation": "imports_from", "confidence": "EXTRACTED", "source_file": "frontend\\components\\header\\DesktopNav.tsx", "source_location": "L9", "weight": 1.0}, {"source": "desktopnav", "target": "design_system", "relation": "imports_from", "confidence": "EXTRACTED", "source_file": "frontend\\components\\header\\DesktopNav.tsx", "source_location": "L10", "weight": 1.0}, {"source": "desktopnav", "target": "button", "relation": "imports_from", "confidence": "EXTRACTED", "source_file": "frontend\\components\\header\\DesktopNav.tsx", "source_location": "L11", "weight": 1.0}, {"source": "desktopnav", "target": "desktopnav_desktopnav", "relation": "contains", "confidence": "EXTRACTED", "source_file": "frontend\\components\\header\\DesktopNav.tsx", "source_location": "L24", "weight": 1.0}]}