{"nodes": [{"id": "s_mls_v2_frontend_app_root_map_search_page_tsx", "label": "page.tsx", "file_type": "code", "source_file": "S:\\mls-v2\\frontend\\app\\(root)\\map-search\\page.tsx", "source_location": "L1"}, {"id": "page_onfinishdrawing", "label": "onFinishDrawing()", "file_type": "code", "source_file": "S:\\mls-v2\\frontend\\app\\(root)\\map-search\\page.tsx", "source_location": "L118"}, {"id": "page_ondocclick", "label": "onDocClick()", "file_type": "code", "source_file": "S:\\mls-v2\\frontend\\app\\(root)\\map-search\\page.tsx", "source_location": "L210"}, {"id": "page_updaterect", "label": "updateRect()", "file_type": "code", "source_file": "S:\\mls-v2\\frontend\\app\\(root)\\map-search\\page.tsx", "source_location": "L231"}, {"id": "page_handlemapready", "label": "handleMapReady()", "file_type": "code", "source_file": "S:\\mls-v2\\frontend\\app\\(root)\\map-search\\page.tsx", "source_location": "L257"}, {"id": "page_clearall", "label": "clearAll()", "file_type": "code", "source_file": "S:\\mls-v2\\frontend\\app\\(root)\\map-search\\page.tsx", "source_location": "L277"}, {"id": "page_handleviewonmap", "label": "handleViewOnMap()", "file_type": "code", "source_file": "S:\\mls-v2\\frontend\\app\\(root)\\map-search\\page.tsx", "source_location": "L290"}, {"id": "page_handleviewstreetview", "label": "handleViewStreetView()", "file_type": "code", "source_file": "S:\\mls-v2\\frontend\\app\\(root)\\map-search\\page.tsx", "source_location": "L303"}, {"id": "page_onsearchkeydown", "label": "onSearchKeyDown()", "file_type": "code", "source_file": "S:\\mls-v2\\frontend\\app\\(root)\\map-search\\page.tsx", "source_location": "L310"}, {"id": "page_onaggregatecellclick", "label": "onAggregateCellClick()", "file_type": "code", "source_file": "S:\\mls-v2\\frontend\\app\\(root)\\map-search\\page.tsx", "source_location": "L338"}], "edges": [{"source": "s_mls_v2_frontend_app_root_map_search_page_tsx", "target": "react", "relation": "imports_from", "confidence": "EXTRACTED", "source_file": "S:\\mls-v2\\frontend\\app\\(root)\\map-search\\page.tsx", "source_location": "L3", "weight": 1.0}, {"source": "s_mls_v2_frontend_app_root_map_search_page_tsx", "target": "dynamic", "relation": "imports_from", "confidence": "EXTRACTED", "source_file": "S:\\mls-v2\\frontend\\app\\(root)\\map-search\\page.tsx", "source_location": "L4", "weight": 1.0}, {"source": "s_mls_v2_frontend_app_root_map_search_page_tsx", "target": "lucide_react", "relation": "imports_from", "confidence": "EXTRACTED", "source_file": "S:\\mls-v2\\frontend\\app\\(root)\\map-search\\page.tsx", "source_location": "L5", "weight": 1.0}, {"source": "s_mls_v2_frontend_app_root_map_search_page_tsx", "target": "env", "relation": "imports_from", "confidence": "EXTRACTED", "source_file": "S:\\mls-v2\\frontend\\app\\(root)\\map-search\\page.tsx", "source_location": "L6", "weight": 1.0}, {"source": "s_mls_v2_frontend_app_root_map_search_page_tsx", "target": "header", "relation": "imports_from", "confidence": "EXTRACTED", "source_file": "S:\\mls-v2\\frontend\\app\\(root)\\map-search\\page.tsx", "source_location": "L9", "weight": 1.0}, {"source": "s_mls_v2_frontend_app_root_map_search_page_tsx", "target": "searchportal", "relation": "imports_from", "confidence": "EXTRACTED", "source_file": "S:\\mls-v2\\frontend\\app\\(root)\\map-search\\page.tsx", "source_location": "L10", "weight": 1.0}, {"source": "s_mls_v2_frontend_app_root_map_search_page_tsx", "target": "mapcontroller", "relation": "imports_from", "confidence": "EXTRACTED", "source_file": "S:\\mls-v2\\frontend\\app\\(root)\\map-search\\page.tsx", "source_location": "L11", "weight": 1.0}, {"source": "s_mls_v2_frontend_app_root_map_search_page_tsx", "target": "streetviewbutton", "relation": "imports_from", "confidence": "EXTRACTED", "source_file": "S:\\mls-v2\\frontend\\app\\(root)\\map-search\\page.tsx", "source_location": "L12", "weight": 1.0}, {"source": "s_mls_v2_frontend_app_root_map_search_page_tsx", "target": "mapsidebar", "relation": "imports_from", "confidence": "EXTRACTED", "source_file": "S:\\mls-v2\\frontend\\app\\(root)\\map-search\\page.tsx", "source_location": "L13", "weight": 1.0}, {"source": "s_mls_v2_frontend_app_root_map_search_page_tsx", "target": "mapoverlaycontrols", "relation": "imports_from", "confidence": "EXTRACTED", "source_file": "S:\\mls-v2\\frontend\\app\\(root)\\map-search\\page.tsx", "source_location": "L14", "weight": 1.0}, {"source": "s_mls_v2_frontend_app_root_map_search_page_tsx", "target": "searchthisareabutton", "relation": "imports_from", "confidence": "EXTRACTED", "source_file": "S:\\mls-v2\\frontend\\app\\(root)\\map-search\\page.tsx", "source_location": "L15", "weight": 1.0}, {"source": "s_mls_v2_frontend_app_root_map_search_page_tsx", "target": "usemapsearch", "relation": "imports_from", "confidence": "EXTRACTED", "source_file": "S:\\mls-v2\\frontend\\app\\(root)\\map-search\\page.tsx", "source_location": "L18", "weight": 1.0}, {"source": "s_mls_v2_frontend_app_root_map_search_page_tsx", "target": "usegeocoding", "relation": "imports_from", "confidence": "EXTRACTED", "source_file": "S:\\mls-v2\\frontend\\app\\(root)\\map-search\\page.tsx", "source_location": "L19", "weight": 1.0}, {"source": "s_mls_v2_frontend_app_root_map_search_page_tsx", "target": "usemapdrawing", "relation": "imports_from", "confidence": "EXTRACTED", "source_file": "S:\\mls-v2\\frontend\\app\\(root)\\map-search\\page.tsx", "source_location": "L20", "weight": 1.0}, {"source": "s_mls_v2_frontend_app_root_map_search_page_tsx", "target": "mapicons", "relation": "imports_from", "confidence": "EXTRACTED", "source_file": "S:\\mls-v2\\frontend\\app\\(root)\\map-search\\page.tsx", "source_location": "L21", "weight": 1.0}, {"source": "s_mls_v2_frontend_app_root_map_search_page_tsx", "target": "helpers", "relation": "imports_from", "confidence": "EXTRACTED", "source_file": "S:\\mls-v2\\frontend\\app\\(root)\\map-search\\page.tsx", "source_location": "L22", "weight": 1.0}, {"source": "s_mls_v2_frontend_app_root_map_search_page_tsx", "target": "propertyutils", "relation": "imports_from", "confidence": "EXTRACTED", "source_file": "S:\\mls-v2\\frontend\\app\\(root)\\map-search\\page.tsx", "source_location": "L23", "weight": 1.0}, {"source": "s_mls_v2_frontend_app_root_map_search_page_tsx", "target": "openinnewtab", "relation": "imports_from", "confidence": "EXTRACTED", "source_file": "S:\\mls-v2\\frontend\\app\\(root)\\map-search\\page.tsx", "source_location": "L24", "weight": 1.0}, {"source": "s_mls_v2_frontend_app_root_map_search_page_tsx", "target": "types", "relation": "imports_from", "confidence": "EXTRACTED", "source_file": "S:\\mls-v2\\frontend\\app\\(root)\\map-search\\page.tsx", "source_location": "L27", "weight": 1.0}, {"source": "s_mls_v2_frontend_app_root_map_search_page_tsx", "target": "usemapaggregates", "relation": "imports_from", "confidence": "EXTRACTED", "source_file": "S:\\mls-v2\\frontend\\app\\(root)\\map-search\\page.tsx", "source_location": "L28", "weight": 1.0}, {"source": "s_mls_v2_frontend_app_root_map_search_page_tsx", "target": "types", "relation": "imports_from", "confidence": "EXTRACTED", "source_file": "S:\\mls-v2\\frontend\\app\\(root)\\map-search\\page.tsx", "source_location": "L29", "weight": 1.0}, {"source": "s_mls_v2_frontend_app_root_map_search_page_tsx", "target": "watchedcontext", "relation": "imports_from", "confidence": "EXTRACTED", "source_file": "S:\\mls-v2\\frontend\\app\\(root)\\map-search\\page.tsx", "source_location": "L30", "weight": 1.0}, {"source": "s_mls_v2_frontend_app_root_map_search_page_tsx", "target": "polygon", "relation": "imports_from", "confidence": "EXTRACTED", "source_file": "S:\\mls-v2\\frontend\\app\\(root)\\map-search\\page.tsx", "source_location": "L31", "weight": 1.0}, {"source": "s_mls_v2_frontend_app_root_map_search_page_tsx", "target": "page_onfinishdrawing", "relation": "contains", "confidence": "EXTRACTED", "source_file": "S:\\mls-v2\\frontend\\app\\(root)\\map-search\\page.tsx", "source_location": "L118", "weight": 1.0}, {"source": "s_mls_v2_frontend_app_root_map_search_page_tsx", "target": "page_ondocclick", "relation": "contains", "confidence": "EXTRACTED", "source_file": "S:\\mls-v2\\frontend\\app\\(root)\\map-search\\page.tsx", "source_location": "L210", "weight": 1.0}, {"source": "s_mls_v2_frontend_app_root_map_search_page_tsx", "target": "page_updaterect", "relation": "contains", "confidence": "EXTRACTED", "source_file": "S:\\mls-v2\\frontend\\app\\(root)\\map-search\\page.tsx", "source_location": "L231", "weight": 1.0}, {"source": "s_mls_v2_frontend_app_root_map_search_page_tsx", "target": "page_handlemapready", "relation": "contains", "confidence": "EXTRACTED", "source_file": "S:\\mls-v2\\frontend\\app\\(root)\\map-search\\page.tsx", "source_location": "L257", "weight": 1.0}, {"source": "s_mls_v2_frontend_app_root_map_search_page_tsx", "target": "page_clearall", "relation": "contains", "confidence": "EXTRACTED", "source_file": "S:\\mls-v2\\frontend\\app\\(root)\\map-search\\page.tsx", "source_location": "L277", "weight": 1.0}, {"source": "s_mls_v2_frontend_app_root_map_search_page_tsx", "target": "page_handleviewonmap", "relation": "contains", "confidence": "EXTRACTED", "source_file": "S:\\mls-v2\\frontend\\app\\(root)\\map-search\\page.tsx", "source_location": "L290", "weight": 1.0}, {"source": "s_mls_v2_frontend_app_root_map_search_page_tsx", "target": "page_handleviewstreetview", "relation": "contains", "confidence": "EXTRACTED", "source_file": "S:\\mls-v2\\frontend\\app\\(root)\\map-search\\page.tsx", "source_location": "L303", "weight": 1.0}, {"source": "s_mls_v2_frontend_app_root_map_search_page_tsx", "target": "page_onsearchkeydown", "relation": "contains", "confidence": "EXTRACTED", "source_file": "S:\\mls-v2\\frontend\\app\\(root)\\map-search\\page.tsx", "source_location": "L310", "weight": 1.0}, {"source": "s_mls_v2_frontend_app_root_map_search_page_tsx", "target": "page_onaggregatecellclick", "relation": "contains", "confidence": "EXTRACTED", "source_file": "S:\\mls-v2\\frontend\\app\\(root)\\map-search\\page.tsx", "source_location": "L338", "weight": 1.0}], "raw_calls": [{"caller_nid": "page_onfinishdrawing", "callee": "setLoadingApi", "source_file": "S:\\mls-v2\\frontend\\app\\(root)\\map-search\\page.tsx", "source_location": "L132"}, {"caller_nid": "page_onfinishdrawing", "callee": "setApiError", "source_file": "S:\\mls-v2\\frontend\\app\\(root)\\map-search\\page.tsx", "source_location": "L133"}, {"caller_nid": "page_onfinishdrawing", "callee": "setApiMarkers", "source_file": "S:\\mls-v2\\frontend\\app\\(root)\\map-search\\page.tsx", "source_location": "L134"}, {"caller_nid": "page_onfinishdrawing", "callee": "setAggregateMarkers", "source_file": "S:\\mls-v2\\frontend\\app\\(root)\\map-search\\page.tsx", "source_location": "L135"}, {"caller_nid": "page_onfinishdrawing", "callee": "setMapDataMode", "source_file": "S:\\mls-v2\\frontend\\app\\(root)\\map-search\\page.tsx", "source_location": "L136"}, {"caller_nid": "page_onfinishdrawing", "callee": "setSelectedPropertyId", "source_file": "S:\\mls-v2\\frontend\\app\\(root)\\map-search\\page.tsx", "source_location": "L137"}, {"caller_nid": "page_onfinishdrawing", "callee": "fetchExclusivePropertiesForBBox", "source_file": "S:\\mls-v2\\frontend\\app\\(root)\\map-search\\page.tsx", "source_location": "L139"}, {"caller_nid": "page_onfinishdrawing", "callee": "filter", "source_file": "S:\\mls-v2\\frontend\\app\\(root)\\map-search\\page.tsx", "source_location": "L142"}, {"caller_nid": "page_onfinishdrawing", "callee": "filter", "source_file": "S:\\mls-v2\\frontend\\app\\(root)\\map-search\\page.tsx", "source_location": "L151"}, {"caller_nid": "page_onfinishdrawing", "callee": "map", "source_file": "S:\\mls-v2\\frontend\\app\\(root)\\map-search\\page.tsx", "source_location": "L151"}, {"caller_nid": "page_onfinishdrawing", "callee": "setApiMarkers", "source_file": "S:\\mls-v2\\frontend\\app\\(root)\\map-search\\page.tsx", "source_location": "L174"}, {"caller_nid": "page_onfinishdrawing", "callee": "map", "source_file": "S:\\mls-v2\\frontend\\app\\(root)\\map-search\\page.tsx", "source_location": "L177"}, {"caller_nid": "page_onfinishdrawing", "callee": "latLngBounds", "source_file": "S:\\mls-v2\\frontend\\app\\(root)\\map-search\\page.tsx", "source_location": "L178"}, {"caller_nid": "page_onfinishdrawing", "callee": "fitBounds", "source_file": "S:\\mls-v2\\frontend\\app\\(root)\\map-search\\page.tsx", "source_location": "L179"}, {"caller_nid": "page_onfinishdrawing", "callee": "pad", "source_file": "S:\\mls-v2\\frontend\\app\\(root)\\map-search\\page.tsx", "source_location": "L179"}, {"caller_nid": "page_onfinishdrawing", "callee": "setLoadingApi", "source_file": "S:\\mls-v2\\frontend\\app\\(root)\\map-search\\page.tsx", "source_location": "L182"}, {"caller_nid": "page_onfinishdrawing", "callee": "error", "source_file": "S:\\mls-v2\\frontend\\app\\(root)\\map-search\\page.tsx", "source_location": "L184"}, {"caller_nid": "page_onfinishdrawing", "callee": "setApiError", "source_file": "S:\\mls-v2\\frontend\\app\\(root)\\map-search\\page.tsx", "source_location": "L185"}, {"caller_nid": "page_onfinishdrawing", "callee": "setLoadingApi", "source_file": "S:\\mls-v2\\frontend\\app\\(root)\\map-search\\page.tsx", "source_location": "L186"}, {"caller_nid": "page_ondocclick", "callee": "contains", "source_file": "S:\\mls-v2\\frontend\\app\\(root)\\map-search\\page.tsx", "source_location": "L211"}, {"caller_nid": "page_ondocclick", "callee": "setTimeout", "source_file": "S:\\mls-v2\\frontend\\app\\(root)\\map-search\\page.tsx", "source_location": "L214"}, {"caller_nid": "page_updaterect", "callee": "setAnchorRect", "source_file": "S:\\mls-v2\\frontend\\app\\(root)\\map-search\\page.tsx", "source_location": "L233"}, {"caller_nid": "page_updaterect", "callee": "getBoundingClientRect", "source_file": "S:\\mls-v2\\frontend\\app\\(root)\\map-search\\page.tsx", "source_location": "L233"}, {"caller_nid": "page_handlemapready", "callee": "enable", "source_file": "S:\\mls-v2\\frontend\\app\\(root)\\map-search\\page.tsx", "source_location": "L260"}, {"caller_nid": "page_handlemapready", "callee": "on", "source_file": "S:\\mls-v2\\frontend\\app\\(root)\\map-search\\page.tsx", "source_location": "L263"}, {"caller_nid": "page_handlemapready", "callee": "on", "source_file": "S:\\mls-v2\\frontend\\app\\(root)\\map-search\\page.tsx", "source_location": "L266"}, {"caller_nid": "page_handlemapready", "callee": "handleSearchThisArea", "source_file": "S:\\mls-v2\\frontend\\app\\(root)\\map-search\\page.tsx", "source_location": "L272"}, {"caller_nid": "page_clearall", "callee": "clearShape", "source_file": "S:\\mls-v2\\frontend\\app\\(root)\\map-search\\page.tsx", "source_location": "L278"}, {"caller_nid": "page_clearall", "callee": "setApiMarkers", "source_file": "S:\\mls-v2\\frontend\\app\\(root)\\map-search\\page.tsx", "source_location": "L279"}, {"caller_nid": "page_clearall", "callee": "setAggregateMarkers", "source_file": "S:\\mls-v2\\frontend\\app\\(root)\\map-search\\page.tsx", "source_location": "L280"}, {"caller_nid": "page_clearall", "callee": "setMapDataMode", "source_file": "S:\\mls-v2\\frontend\\app\\(root)\\map-search\\page.tsx", "source_location": "L281"}, {"caller_nid": "page_clearall", "callee": "setApiError", "source_file": "S:\\mls-v2\\frontend\\app\\(root)\\map-search\\page.tsx", "source_location": "L282"}, {"caller_nid": "page_clearall", "callee": "setLoadingApi", "source_file": "S:\\mls-v2\\frontend\\app\\(root)\\map-search\\page.tsx", "source_location": "L283"}, {"caller_nid": "page_clearall", "callee": "setSelectedPropertyId", "source_file": "S:\\mls-v2\\frontend\\app\\(root)\\map-search\\page.tsx", "source_location": "L284"}, {"caller_nid": "page_clearall", "callee": "setSelectedAggregateId", "source_file": "S:\\mls-v2\\frontend\\app\\(root)\\map-search\\page.tsx", "source_location": "L285"}, {"caller_nid": "page_clearall", "callee": "setShowSearchThisArea", "source_file": "S:\\mls-v2\\frontend\\app\\(root)\\map-search\\page.tsx", "source_location": "L286"}, {"caller_nid": "page_clearall", "callee": "resetMapFetchDedupe", "source_file": "S:\\mls-v2\\frontend\\app\\(root)\\map-search\\page.tsx", "source_location": "L287"}, {"caller_nid": "page_handleviewonmap", "callee": "setSelectedPropertyId", "source_file": "S:\\mls-v2\\frontend\\app\\(root)\\map-search\\page.tsx", "source_location": "L291"}, {"caller_nid": "page_handleviewonmap", "callee": "addToHistory", "source_file": "S:\\mls-v2\\frontend\\app\\(root)\\map-search\\page.tsx", "source_location": "L293"}, {"caller_nid": "page_handleviewonmap", "callee": "flyTo", "source_file": "S:\\mls-v2\\frontend\\app\\(root)\\map-search\\page.tsx", "source_location": "L296"}, {"caller_nid": "page_handleviewstreetview", "callee": "open", "source_file": "S:\\mls-v2\\frontend\\app\\(root)\\map-search\\page.tsx", "source_location": "L304"}, {"caller_nid": "page_onsearchkeydown", "callee": "preventDefault", "source_file": "S:\\mls-v2\\frontend\\app\\(root)\\map-search\\page.tsx", "source_location": "L312"}, {"caller_nid": "page_onsearchkeydown", "callee": "Number", "source_file": "S:\\mls-v2\\frontend\\app\\(root)\\map-search\\page.tsx", "source_location": "L315"}, {"caller_nid": "page_onsearchkeydown", "callee": "Number", "source_file": "S:\\mls-v2\\frontend\\app\\(root)\\map-search\\page.tsx", "source_location": "L316"}, {"caller_nid": "page_onsearchkeydown", "callee": "setSearchResult", "source_file": "S:\\mls-v2\\frontend\\app\\(root)\\map-search\\page.tsx", "source_location": "L317"}, {"caller_nid": "page_onsearchkeydown", "callee": "setResultsOpen", "source_file": "S:\\mls-v2\\frontend\\app\\(root)\\map-search\\page.tsx", "source_location": "L318"}, {"caller_nid": "page_onsearchkeydown", "callee": "setSearchResults", "source_file": "S:\\mls-v2\\frontend\\app\\(root)\\map-search\\page.tsx", "source_location": "L319"}, {"caller_nid": "page_onsearchkeydown", "callee": "flyTo", "source_file": "S:\\mls-v2\\frontend\\app\\(root)\\map-search\\page.tsx", "source_location": "L321"}, {"caller_nid": "page_onaggregatecellclick", "callee": "getZoom", "source_file": "S:\\mls-v2\\frontend\\app\\(root)\\map-search\\page.tsx", "source_location": "L341"}, {"caller_nid": "page_onaggregatecellclick", "callee": "getDrillTargetZoom", "source_file": "S:\\mls-v2\\frontend\\app\\(root)\\map-search\\page.tsx", "source_location": "L342"}, {"caller_nid": "page_onaggregatecellclick", "callee": "setSelectedAggregateId", "source_file": "S:\\mls-v2\\frontend\\app\\(root)\\map-search\\page.tsx", "source_location": "L346"}, {"caller_nid": "page_onaggregatecellclick", "callee": "setSelectedPropertyId", "source_file": "S:\\mls-v2\\frontend\\app\\(root)\\map-search\\page.tsx", "source_location": "L347"}, {"caller_nid": "page_onaggregatecellclick", "callee": "setLoadingApi", "source_file": "S:\\mls-v2\\frontend\\app\\(root)\\map-search\\page.tsx", "source_location": "L348"}, {"caller_nid": "page_onaggregatecellclick", "callee": "setShowSearchThisArea", "source_file": "S:\\mls-v2\\frontend\\app\\(root)\\map-search\\page.tsx", "source_location": "L349"}, {"caller_nid": "page_onaggregatecellclick", "callee": "once", "source_file": "S:\\mls-v2\\frontend\\app\\(root)\\map-search\\page.tsx", "source_location": "L353"}, {"caller_nid": "page_onaggregatecellclick", "callee": "flyTo", "source_file": "S:\\mls-v2\\frontend\\app\\(root)\\map-search\\page.tsx", "source_location": "L355"}, {"caller_nid": "page_onaggregatecellclick", "callee": "off", "source_file": "S:\\mls-v2\\frontend\\app\\(root)\\map-search\\page.tsx", "source_location": "L360"}, {"caller_nid": "page_onaggregatecellclick", "callee": "setLoadingApi", "source_file": "S:\\mls-v2\\frontend\\app\\(root)\\map-search\\page.tsx", "source_location": "L361"}]}