{"nodes": [{"id": "s_mls_v2_frontend_data_listingdetails_ts", "label": "listingDetails.ts", "file_type": "code", "source_file": "S:\\mls-v2\\frontend\\data\\listingDetails.ts", "source_location": "L1"}, {"id": "listingdetails_generatelistingdetails", "label": "generateListingDetails()", "file_type": "code", "source_file": "S:\\mls-v2\\frontend\\data\\listingDetails.ts", "source_location": "L90"}, {"id": "listingdetails_getlistingdetails", "label": "getListingDetails()", "file_type": "code", "source_file": "S:\\mls-v2\\frontend\\data\\listingDetails.ts", "source_location": "L298"}], "edges": [{"source": "s_mls_v2_frontend_data_listingdetails_ts", "target": "s_mls_v2_frontend_data_listings", "relation": "imports_from", "confidence": "EXTRACTED", "source_file": "S:\\mls-v2\\frontend\\data\\listingDetails.ts", "source_location": "L2", "weight": 1.0}, {"source": "s_mls_v2_frontend_data_listingdetails_ts", "target": "listingdetails_generatelistingdetails", "relation": "contains", "confidence": "EXTRACTED", "source_file": "S:\\mls-v2\\frontend\\data\\listingDetails.ts", "source_location": "L90", "weight": 1.0}, {"source": "s_mls_v2_frontend_data_listingdetails_ts", "target": "listingdetails_getlistingdetails", "relation": "contains", "confidence": "EXTRACTED", "source_file": "S:\\mls-v2\\frontend\\data\\listingDetails.ts", "source_location": "L298", "weight": 1.0}], "raw_calls": [{"caller_nid": "listingdetails_generatelistingdetails", "callee": "replace", "source_file": "S:\\mls-v2\\frontend\\data\\listingDetails.ts", "source_location": "L120"}, {"caller_nid": "listingdetails_generatelistingdetails", "callee": "replace", "source_file": "S:\\mls-v2\\frontend\\data\\listingDetails.ts", "source_location": "L120"}]}