{"nodes": [{"id": "newslettersection", "label": "NewsletterSection.tsx", "file_type": "code", "source_file": "frontend\\components\\homepage\\NewsletterSection.tsx", "source_location": "L1"}, {"id": "newslettersection_newslettersection", "label": "NewsletterSection()", "file_type": "code", "source_file": "frontend\\components\\homepage\\NewsletterSection.tsx", "source_location": "L9"}], "edges": [{"source": "newslettersection", "target": "react", "relation": "imports_from", "confidence": "EXTRACTED", "source_file": "frontend\\components\\homepage\\NewsletterSection.tsx", "source_location": "L3", "weight": 1.0}, {"source": "newslettersection", "target": "framer_motion", "relation": "imports_from", "confidence": "EXTRACTED", "source_file": "frontend\\components\\homepage\\NewsletterSection.tsx", "source_location": "L4", "weight": 1.0}, {"source": "newslettersection", "target": "config", "relation": "imports_from", "confidence": "EXTRACTED", "source_file": "frontend\\components\\homepage\\NewsletterSection.tsx", "source_location": "L5", "weight": 1.0}, {"source": "newslettersection", "target": "button", "relation": "imports_from", "confidence": "EXTRACTED", "source_file": "frontend\\components\\homepage\\NewsletterSection.tsx", "source_location": "L6", "weight": 1.0}, {"source": "newslettersection", "target": "input", "relation": "imports_from", "confidence": "EXTRACTED", "source_file": "frontend\\components\\homepage\\NewsletterSection.tsx", "source_location": "L7", "weight": 1.0}, {"source": "newslettersection", "target": "newslettersection_newslettersection", "relation": "contains", "confidence": "EXTRACTED", "source_file": "frontend\\components\\homepage\\NewsletterSection.tsx", "source_location": "L9", "weight": 1.0}]}