{"nodes": [{"id": "frontend_components_ui_pillbutton_tsx", "label": "PillButton.tsx", "file_type": "code", "source_file": "frontend\\components\\ui\\PillButton.tsx", "source_location": "L1"}, {"id": "pillbutton_pillbutton", "label": "PillButton()", "file_type": "code", "source_file": "frontend\\components\\ui\\PillButton.tsx", "source_location": "L14"}], "edges": [{"source": "frontend_components_ui_pillbutton_tsx", "target": "react", "relation": "imports_from", "confidence": "EXTRACTED", "source_file": "frontend\\components\\ui\\PillButton.tsx", "source_location": "L3", "weight": 1.0}, {"source": "frontend_components_ui_pillbutton_tsx", "target": "design_system", "relation": "imports_from", "confidence": "EXTRACTED", "source_file": "frontend\\components\\ui\\PillButton.tsx", "source_location": "L4", "weight": 1.0}, {"source": "frontend_components_ui_pillbutton_tsx", "target": "pillbutton_pillbutton", "relation": "contains", "confidence": "EXTRACTED", "source_file": "frontend\\components\\ui\\PillButton.tsx", "source_location": "L14", "weight": 1.0}]}