{"nodes": [{"id": "frontend_components_homepage_listingdetails_tsx", "label": "ListingDetails.tsx", "file_type": "code", "source_file": "frontend\\components\\homepage\\ListingDetails.tsx", "source_location": "L1"}, {"id": "listingdetails_listingdetails", "label": "ListingDetails()", "file_type": "code", "source_file": "frontend\\components\\homepage\\ListingDetails.tsx", "source_location": "L17"}], "edges": [{"source": "frontend_components_homepage_listingdetails_tsx", "target": "react", "relation": "imports_from", "confidence": "EXTRACTED", "source_file": "frontend\\components\\homepage\\ListingDetails.tsx", "source_location": "L3", "weight": 1.0}, {"source": "frontend_components_homepage_listingdetails_tsx", "target": "navigation", "relation": "imports_from", "confidence": "EXTRACTED", "source_file": "frontend\\components\\homepage\\ListingDetails.tsx", "source_location": "L4", "weight": 1.0}, {"source": "frontend_components_homepage_listingdetails_tsx", "target": "header", "relation": "imports_from", "confidence": "EXTRACTED", "source_file": "frontend\\components\\homepage\\ListingDetails.tsx", "source_location": "L5", "weight": 1.0}, {"source": "frontend_components_homepage_listingdetails_tsx", "target": "propertygallery", "relation": "imports_from", "confidence": "EXTRACTED", "source_file": "frontend\\components\\homepage\\ListingDetails.tsx", "source_location": "L6", "weight": 1.0}, {"source": "frontend_components_homepage_listingdetails_tsx", "target": "propertypricingsection", "relation": "imports_from", "confidence": "EXTRACTED", "source_file": "frontend\\components\\homepage\\ListingDetails.tsx", "source_location": "L7", "weight": 1.0}, {"source": "frontend_components_homepage_listingdetails_tsx", "target": "propertyactionbuttons", "relation": "imports_from", "confidence": "EXTRACTED", "source_file": "frontend\\components\\homepage\\ListingDetails.tsx", "source_location": "L8", "weight": 1.0}, {"source": "frontend_components_homepage_listingdetails_tsx", "target": "propertymap", "relation": "imports_from", "confidence": "EXTRACTED", "source_file": "frontend\\components\\homepage\\ListingDetails.tsx", "source_location": "L9", "weight": 1.0}, {"source": "frontend_components_homepage_listingdetails_tsx", "target": "nearbylistings", "relation": "imports_from", "confidence": "EXTRACTED", "source_file": "frontend\\components\\homepage\\ListingDetails.tsx", "source_location": "L10", "weight": 1.0}, {"source": "frontend_components_homepage_listingdetails_tsx", "target": "listingdetails", "relation": "imports_from", "confidence": "EXTRACTED", "source_file": "frontend\\components\\homepage\\ListingDetails.tsx", "source_location": "L11", "weight": 1.0}, {"source": "frontend_components_homepage_listingdetails_tsx", "target": "listingtabs", "relation": "imports_from", "confidence": "EXTRACTED", "source_file": "frontend\\components\\homepage\\ListingDetails.tsx", "source_location": "L14", "weight": 1.0}, {"source": "frontend_components_homepage_listingdetails_tsx", "target": "listinginsights", "relation": "imports_from", "confidence": "EXTRACTED", "source_file": "frontend\\components\\homepage\\ListingDetails.tsx", "source_location": "L15", "weight": 1.0}, {"source": "frontend_components_homepage_listingdetails_tsx", "target": "listingdetails_listingdetails", "relation": "contains", "confidence": "EXTRACTED", "source_file": "frontend\\components\\homepage\\ListingDetails.tsx", "source_location": "L17", "weight": 1.0}]}